icalendar_events_cli-1.0.1.dist-info/METADATA
icalendar_events_cli-1.0.1.dist-info/WHEEL
icalendar_events_cli-1.0.1.dist-info/entry_points.txt
icalendar_events_cli-1.0.1.dist-info/licenses/LICENSE
icalendar_events_cli/__init__.py
icalendar_events_cli/__main__.py
icalendar_events_cli/argparse.py
icalendar_events_cli/downloader.py
icalendar_events_cli/icalendar.py
icalendar_events_cli/output.py
icalendar_events_cli-1.0.1.dist-info/RECORD
