Metadata-Version: 2.1
Name: icalendar-events-cli
Version: 1.0.1
Summary: Command-line tool to read events from a iCalendar (ICS)
Author-Email: Sebastian Waldvogel <sebastian@waldvogels.de>
License: MIT
Project-URL: Repository, https://github.com/waldbaer/icalendar-events-cli
Requires-Python: >=3.9
Requires-Dist: tzlocal==5.3.1
Requires-Dist: pytz==2025.2
Requires-Dist: recurring-ical-events==3.6.0
Requires-Dist: requests==2.32.3
Requires-Dist: requests-file==2.1.0
Requires-Dist: jsonargparse==4.38.0
Requires-Dist: rich-argparse==1.7.0
Requires-Dist: pydantic==2.11.1
